plateau/__init__.py
plateau/api/__init__.py
plateau/api/dataset.py
plateau/api/serialization.py
plateau/core/__init__.py
plateau/core/_compat.py
plateau/core/_deprecation.py
plateau/core/_mixins.py
plateau/core/_time.py
plateau/core/_zmsgpack.py
plateau/core/common_metadata.py
plateau/core/dataset.py
plateau/core/docs.py
plateau/core/factory.py
plateau/core/index.py
plateau/core/naming.py
plateau/core/partition.py
plateau/core/testing.py
plateau/core/typing.py
plateau/core/urlencode.py
plateau/core/utils.py
plateau/core/uuid.py
plateau/io/__init__.py
plateau/io/eager.py
plateau/io/iter.py
plateau/io/dask/__init__.py
plateau/io/dask/_shuffle.py
plateau/io/dask/_sizeof.py
plateau/io/dask/_utils.py
plateau/io/dask/bag.py
plateau/io/dask/compression.py
plateau/io/dask/dataframe.py
plateau/io/dask/delayed.py
plateau/io/testing/__init__.py
plateau/io/testing/delete.py
plateau/io/testing/gc.py
plateau/io/testing/index.py
plateau/io/testing/read.py
plateau/io/testing/update.py
plateau/io/testing/utils.py
plateau/io/testing/write.py
plateau/io_components/__init__.py
plateau/io_components/delete.py
plateau/io_components/gc.py
plateau/io_components/index.py
plateau/io_components/metapartition.py
plateau/io_components/read.py
plateau/io_components/update.py
plateau/io_components/utils.py
plateau/io_components/write.py
plateau/serialization/__init__.py
plateau/serialization/_csv.py
plateau/serialization/_generic.py
plateau/serialization/_io_buffer.py
plateau/serialization/_parquet.py
plateau/serialization/_util.py
plateau/serialization/testing.py
plateau/utils/__init__.py
plateau/utils/converters.py
plateau/utils/pandas.py
plateau/utils/store.py
plateau-4.6.2.dist-info/licenses/LICENSE.txt
plateau-4.6.2.dist-info/METADATA
plateau-4.6.2.dist-info/WHEEL
plateau-4.6.2.dist-info/top_level.txt
plateau-4.6.2.dist-info/RECORD
