Metadata-Version: 2.4
Name: plateau
Version: 4.6.2
Summary: A Python library to manage (create, read, update, delete) large amounts of tabular data in a blob store.
Author-email: Data Engineering Collective <plateau@uwekorn.com>
License: MIT License
Project-URL: Repository, https://github.com/data-engineering-collective/plateau
Classifier: License :: OSI Approved :: MIT License
Classifier: Programming Language :: Python :: 3
Classifier: Programming Language :: Python :: 3.10
Classifier: Programming Language :: Python :: 3.11
Classifier: Programming Language :: Python :: 3.12
Requires-Python: >=3.10
License-File: LICENSE.txt
Requires-Dist: dask[dataframe]!=2021.5.1,!=2021.6.0
Requires-Dist: decorator
Requires-Dist: msgpack>=0.5.2
Requires-Dist: numpy<3,>1.23
Requires-Dist: pandas>=2
Requires-Dist: pyarrow!=19.0.0,>=15
Requires-Dist: simplejson
Requires-Dist: minimalkv>=1.4.2
Requires-Dist: toolz
Requires-Dist: urlquote>=1.1.3
Requires-Dist: zstandard
Requires-Dist: attrs
Requires-Dist: click
Requires-Dist: prompt-toolkit
Requires-Dist: pyyaml
Dynamic: license-file
